<DOMSymbolItem xmlns:xsi="http://www.w3.org/2001/XMLSchema-instance" xmlns="http://ns.adobe.com/xfl/2008/" name="Graficos Emotigums/Itens coloriveis/Maos/mao27" itemID="4fe38376-0000071b" lastModified="1340310390">
  <timeline>
    <DOMTimeline name="mao27">
      <layers>
        <DOMLayer name="Layer 1" color="#4FFF4F" current="true" isSelected="true">
          <frames>
            <DOMFrame index="0" keyMode="9728">
              <elements>
                <DOMShape selected="true" isDrawingObject="true">
                  <matrix>
                    <Matrix tx="-73.9" ty="-115.7"/>
                  </matrix>
                  <fills>
                    <FillStyle index="1">
                      <SolidColor color="#FE8F17"/>
                    </FillStyle>
                  </fills>
                  <edges>
                    <Edge fillStyle1="1" edges="!1558 2253|1561 2253!1561 2253|1563 2252!1563 2252|1568 2252!1568 2252[1643 2255 1716 2255!1716 2255|1714 2240!1714 2240|1713 2236!1713 2236|1712 2227!1712 2227|1712 2222!1712 2222|1711 2214!1711 2214|1712 2210!1712 2210|1712 2199!1712
 2199|1715 2185!1715 2185|1719 2174!1719 2174|1722 2168!1722 2168|1726 2164!1726 2164|1726 2163!1726 2163|1735 2154!1735 2154|1738 2153!1738 2153|1742 2151!1742 2151|1743 2151!1743 2151|1745 2150!1745 2150|1752 2150!1752 2150[1759 2152
 1756 2164!1756 2164[1755 2171 1751 2189!1751 2189[1749 2213 1767 2237!1767 2237[1787 2259 1814 2271!1814 2271|1823 2412!1823 2412|1702 2419!1702 2419[1622 2428 1593 2434!1593 2434|1585 2434!1585 2434|1584 2433!1584 2433|1582 2432!1582
 2432|1581 2431!1581 2431|1580 2429!1580 2429[1578 2421 1586 2418!1586 2418|1685 2378!1685 2378|1565 2391!1565 2391|1563 2391!1563 2391|1560 2390!1560 2390|1559 2389!1559 2389|1556 2387!1556 2387|1555 2386!1555 2386|1554 2383!1554 2383
[1550 2373 1562 2368!1562 2368|1684 2331!1684 2331|1683 2331!1683 2331|1677 2332!1677 2332|1632 2334!1632 2334|1631 2334!1631 2334|1616 2335!1616 2335|1566 2335!1566 2335|1556 2334!1556 2334[1535 2332 1537 2321!1537 2321|1538 2317!1538
 2317|1538 2315!1538 2315|1540 2313!1540 2313|1542 2312!1542 2312|1544 2310!1544 2310|1546 2310!1546 2310|1549 2309!1549 2309|1682 2298!1682 2298|1683 2298!1683 2298[1572 2280 1560 2275!1560 2275[1549 2270 1551 2259!1551 2259|1553 2256
!1553 2256|1554 2255!1554 2255|1558 2253"/>
                    <Edge cubics="!1585 2434(;1585,2433 1584,2433 1584,2433q1585 2434 1584 2433);"/>
                    <Edge cubics="!1584 2433(;1583,2433 1582,2432 1582,2432q1584 2433 1582 2432);"/>
                    <Edge cubics="!1582 2432(;1582,2432 1581,2432 1581,2431q1582 2432 1581 2431);"/>
                    <Edge cubics="!1581 2431(;1581,2431 1580,2430 1580,2429q1581 2431 1580 2429);"/>
                    <Edge cubics="!1580 2429(;1579,2424 1581,2420 1586,2418q1580 2429Q1578 2421q1586 2418);"/>
                    <Edge cubics="!1586 2418(;1590,2416 1685,2378 1685,2378q1586 2418 1685 2378);"/>
                    <Edge cubics="!1565 2391(;1565,2391 1564,2391 1563,2391q1565 2391 1563 2391);"/>
                    <Edge cubics="!1563 2391(;1562,2390 1561,2390 1560,2390q1563 2391 1560 2390);"/>
                    <Edge cubics="!1560 2390(;1560,2390 1559,2389 1559,2389q1560 2390 1559 2389);"/>
                    <Edge cubics="!1559 2389(;1558,2389 1557,2388 1556,2387q1559 2389 1556 2387);"/>
                    <Edge cubics="!1556 2387(;1556,2387 1556,2387 1555,2386q1556 2387 1555 2386);"/>
                    <Edge cubics="!1555 2386(;1555,2385 1554,2384 1554,2383q1555 2386 1554 2383);"/>
                    <Edge cubics="!1554 2383(;1552,2378 1555,2371 1562,2368q1554 2383Q1550 2373q1562 2368);"/>
                    <Edge cubics="!1562 2368(;1571,2365 1684,2331 1684,2331q1562 2368 1684 2331);"/>
                    <Edge cubics="!1684 2331(;1684,2331 1683,2331 1683,2331q1684 2331 1683 2331);"/>
                    <Edge cubics="!1683 2331(;1682,2331 1680,2331 1677,2332q1683 2331 1677 2332);"/>
                    <Edge cubics="!1632 2334(;1632,2334 1631,2334 1631,2334q1632 2334 1631 2334);"/>
                    <Edge cubics="!1631 2334(;1626,2334 1621,2334 1616,2335q1631 2334 1616 2335);"/>
                    <Edge cubics="!1566 2335(;1562,2335 1559,2335 1556,2334q1566 2335 1556 2334);"/>
                    <Edge cubics="!1556 2334(;1543,2333 1536,2328 1537,2321q1556 2334Q1535 2332q1537 2321);"/>
                    <Edge cubics="!1537 2321(1537,2321;1537,2319 1537,2318 1538,2317q1537 2321 1538 2317);"/>
                    <Edge cubics="!1538 2317(1538,2317;1538,2316 1538,2316 1538,2315q1538 2317 1538 2315);"/>
                    <Edge cubics="!1538 2315(;1539,2315 1539,2314 1540,2313q1538 2315 1540 2313);"/>
                    <Edge cubics="!1540 2313(;1541,2313 1541,2312 1542,2312q1540 2313 1542 2312)1542,2312;"/>
                    <Edge cubics="!1542 2312(;1542,2311 1543,2311 1544,2310q1542 2312 1544 2310);"/>
                    <Edge cubics="!1544 2310(1544,2310;1545,2310 1545,2310 1546,2310q1544 2310 1546 2310);"/>
                    <Edge cubics="!1546 2310(;1547,2310 1548,2309 1549,2309q1546 2310 1549 2309);"/>
                    <Edge cubics="!1549 2309(;1556,2309 1667,2299 1682,2298q1549 2309 1682 2298);"/>
                    <Edge cubics="!1682 2298(;1683,2298 1683,2298 1683,2298q1682 2298 1683 2298);"/>
                    <Edge cubics="!1683 2298(;1683,2298 1572,2280 1560,2275q1683 2298Q1572 2280q1560 2275);"/>
                    <Edge cubics="!1560 2275(;1553,2272 1550,2265 1551,2259q1560 2275Q1549 2270q1551 2259);"/>
                    <Edge cubics="!1551 2259(;1552,2258 1552,2257 1553,2256q1551 2259 1553 2256);"/>
                    <Edge cubics="!1553 2256(;1553,2256 1554,2256 1554,2255q1553 2256 1554 2255);"/>
                    <Edge cubics="!1558 2253(;1559,2253 1560,2253 1561,2253q1558 2253 1561 2253);"/>
                    <Edge cubics="!1561 2253(;1562,2253 1562,2253 1563,2252q1561 2253 1563 2252);"/>
                    <Edge cubics="!1563 2252(;1564,2252 1566,2252 1568,2252q1563 2252 1568 2252);"/>
                    <Edge cubics="!1568 2252(;1618,2254 1684,2255 1716,2255q1568 2252Q1643 2255q1716 2255);"/>
                    <Edge cubics="!1716 2255(;1715,2250 1714,2245 1714,2240q1716 2255 1714 2240);"/>
                    <Edge cubics="!1714 2240(;1713,2239 1713,2237 1713,2236q1714 2240 1713 2236);"/>
                    <Edge cubics="!1713 2236(;1713,2233 1712,2230 1712,2227q1713 2236 1712 2227);"/>
                    <Edge cubics="!1712 2227(;1712,2225 1712,2224 1712,2222q1712 2227 1712 2222);"/>
                    <Edge cubics="!1712 2222(;1711,2219 1711,2217 1711,2214q1712 2222 1711 2214);"/>
                    <Edge cubics="!1711 2214(;1711,2213 1711,2211 1712,2210q1711 2214 1712 2210);"/>
                    <Edge cubics="!1722 2168(;1723,2167 1725,2165 1726,2164q1722 2168 1726 2164);"/>
                    <Edge cubics="!1726 2164(;1726,2163 1726,2163 1726,2163q1726 2164 1726 2163);"/>
                    <Edge cubics="!1735 2154(;1736,2154 1737,2153 1738,2153q1735 2154 1738 2153);"/>
                    <Edge cubics="!1742 2151(;1742,2151 1743,2151 1743,2151q1742 2151 1743 2151);"/>
                    <Edge cubics="!1743 2151(;1744,2150 1745,2150 1745,2150q1743 2151 1745 2150);"/>
                    <Edge cubics="!1752 2150(;1763,2154 1753,2171 1751,2189q1752 2150Q1759 2152q1756 2164Q1755 2171q1751 2189);"/>
                    <Edge cubics="!1751 2189(;1749,2208 1757,2224 1767,2237q1751 2189Q1749 2213q1767 2237);"/>
                    <Edge cubics="!1767 2237(;1782,2253 1801,2265 1814,2271q1767 2237Q1787 2259q1814 2271);"/>
                    <Edge cubics="!1814 2271(;1814,2271 1823,2412 1823,2412q1814 2271 1823 2412);"/>
                    <Edge cubics="!1702 2419(;1701,2420 1622,2428 1593,2434q1702 2419Q1622 2428q1593 2434);"/>
                    <Edge cubics="!1554 2255(;1554,2255 1558,2253 1558,2253q1554 2255 1558 2253);"/>
                    <Edge cubics="!1616 2335(;1616,2335 1566,2335 1566,2335q1616 2335 1566 2335);"/>
                    <Edge cubics="!1593 2434(;1593,2434 1585,2434 1585,2434q1593 2434 1585 2434);"/>
                    <Edge cubics="!1715 2185(;1715,2185 1719,2174 1719,2174q1715 2185 1719 2174);"/>
                    <Edge cubics="!1712 2210(;1712,2210 1712,2199 1712,2199q1712 2210 1712 2199);"/>
                    <Edge cubics="!1712 2199(;1712,2199 1715,2185 1715,2185q1712 2199 1715 2185);"/>
                    <Edge cubics="!1738 2153(;1738,2153 1742,2151 1742,2151q1738 2153 1742 2151);"/>
                    <Edge cubics="!1726 2163(;1726,2163 1735,2154 1735,2154q1726 2163 1735 2154);"/>
                    <Edge cubics="!1745 2150(;1745,2150 1752,2150 1752,2150q1745 2150 1752 2150);"/>
                    <Edge cubics="!1719 2174(;1719,2174 1722,2168 1722,2168q1719 2174 1722 2168);"/>
                    <Edge cubics="!1677 2332(;1677,2332 1632,2334 1632,2334q1677 2332 1632 2334);"/>
                    <Edge cubics="!1823 2412(;1823,2412 1702,2419 1702,2419q1823 2412 1702 2419);"/>
                    <Edge cubics="!1685 2378(;1685,2378 1565,2391 1565,2391q1685 2378 1565 2391);"/>
                  </edges>
                </DOMShape>
                <DOMShape selected="true" isDrawingObject="true">
                  <matrix>
                    <Matrix tx="-73.9" ty="-115.7"/>
                  </matrix>
                  <fills>
                    <FillStyle index="1">
                      <SolidColor color="#FE8F17"/>
                    </FillStyle>
                  </fills>
                  <edges>
                    <Edge fillStyle1="1" edges="
!1307 2320[1315 2319 1318 2327!1318 2327[1320 2338 1313 2342!1313 2342|1287 2358!1287 2358|1318 2356!1318 2356[1326 2355 1330 2366!1330 2366[1334 2378 1328 2380!1328 2380|1293 2395!1293 2395|1331 2394!1331 2394[1336 2394 1339 2410!1339
 2410[1340 2418 1332 2424!1332 2424[1318 2433 1273 2447!1273 2447|1172 2478!1172 2478|1134 2354!1134 2354[1182 2296 1168 2252!1168 2252|1164 2241!1164 2241|1160 2234!1160 2234[1148 2215 1152 2213!1152 2213[1156 2209 1165 2212!1165 2212
[1193 2223 1206 2265!1206 2265[1212 2282 1213 2298!1213 2298|1215 2308!1215 2308|1224 2304!1224 2304[1287 2277 1302 2284!1302 2284[1307 2286 1308 2292!1308 2292[1311 2300 1302 2306!1302 2306|1275 2324!1275 2324|1307 2320"/>
                    <Edge cubics="!1172 2478(;1172,2478 1134,2354 1134,2354q1172 2478p1134 2354);"/>
                    <Edge cubics="!1134 2354(;1149,2336 1181,2293 1168,2252q1134 2354Q1182 2296q1168 2252);"/>
                    <Edge cubics="!1168 2252(;1167,2248 1166,2245 1164,2241q1168 2252 1164 2241);"/>
                    <Edge cubics="!1164 2241(;1164,2241 1160,2234 1160,2234q1164 2241 1160 2234);"/>
                    <Edge cubics="!1160 2234(;1154,2224 1150,2214 1152,2213q1160 2234Q1148 2215q1152 2213);"/>
                    <Edge cubics="!1152 2213(;1153,2212 1158,2210 1165,2212q1152 2213Q1156 2209q1165 2212);"/>
                    <Edge cubics="!1165 2212(;1173,2215 1194,2225 1206,2265q1165 2212Q1193 2223q1206 2265);"/>
                    <Edge cubics="!1206 2265(;1209,2274 1212,2286 1213,2298q1206 2265Q1212 2282q1213 2298);"/>
                    <Edge cubics="!1213 2298(;1213,2298 1215,2308 1215,2308q1213 2298 1215 2308);"/>
                    <Edge cubics="!1215 2308(;1215,2308 1224,2304 1224,2304q1215 2308 1224 2304);"/>
                    <Edge cubics="!1224 2304(;1275,2282 1298,2282 1302,2284q1224 2304Q1287 2277q1302 2284);"/>
                    <Edge cubics="!1302 2284(;1304,2285 1307,2288 1308,2292q1302 2284Q1307 2286q1308 2292);"/>
                    <Edge cubics="!1308 2292(;1310,2298 1308,2302 1302,2306q1308 2292Q1311 2300q1302 2306);"/>
                    <Edge cubics="!1302 2306(;1302,2306 1275,2324 1275,2324q1302 2306 1275 2324);"/>
                    <Edge cubics="!1275 2324(;1275,2324 1307,2320 1307,2320q1275 2324 1307 2320);"/>
                    <Edge cubics="!1307 2320(;1314,2319 1317,2324 1318,2327q1307 2320Q1315 2319q1318 2327);"/>
                    <Edge cubics="!1318 2327(;1319,2332 1318,2339 1313,2342q1318 2327Q1320 2338q1313 2342);"/>
                    <Edge cubics="!1313 2342(;1313,2342 1287,2358 1287,2358q1313 2342 1287 2358);"/>
                    <Edge cubics="!1287 2358(;1287,2358 1318,2356 1318,2356q1287 2358 1318 2356);"/>
                    <Edge cubics="!1318 2356(;1326,2355 1329,2365 1330,2366q1318 2356Q1326 2355q1330 2366);"/>
                    <Edge cubics="!1330 2366(;1332,2373 1331,2379 1328,2380q1330 2366Q1334 2378q1328 2380);"/>
                    <Edge cubics="!1328 2380(;1328,2380 1293,2395 1293,2395q1328 2380 1293 2395);"/>
                    <Edge cubics="!1293 2395(;1293,2395 1331,2394 1331,2394q1293 2395 1331 2394);"/>
                    <Edge cubics="!1331 2394(;1333,2394 1337,2399 1339,2410q1331 2394Q1336 2394q1339 2410);"/>
                    <Edge cubics="!1339 2410(;1340,2418 1341,2426 1273,2447q1339 2410Q1340 2418q1332 2424Q1318 2433q1273 2447);"/>
                    <Edge cubics="!1273 2447(;1230,2460 1192,2472 1172,2478q1273 2447 1172 2478);"/>
                  </edges>
                </DOMShape>
              </elements>
            </DOMFrame>
          </frames>
        </DOMLayer>
      </layers>
    </DOMTimeline>
  </timeline>
</DOMSymbolItem>