<DOMSymbolItem xmlns:xsi="http://www.w3.org/2001/XMLSchema-instance" xmlns="http://ns.adobe.com/xfl/2008/" name="Graficos Emotigums/Itens coloriveis/Maos/mao6" itemID="4fe37c9a-000006a3" lastModified="1340308634">
  <timeline>
    <DOMTimeline name="mao6">
      <layers>
        <DOMLayer name="Layer 1" color="#4FFF4F" current="true" isSelected="true">
          <frames>
            <DOMFrame index="0" keyMode="9728">
              <elements>
                <DOMShape selected="true" isDrawingObject="true">
                  <matrix>
                    <Matrix tx="-74.65" ty="-117.9"/>
                  </matrix>
                  <fills>
                    <FillStyle index="1">
                      <SolidColor color="#FE8F17"/>
                    </FillStyle>
                  </fills>
                  <edges>
                    <Edge fillStyle0="1" edges="!1354 2334|1465 2328!1465 2328[1483 2328 1483 2313!1483 2313[1483 2298 1465 2298!1465 2298|1353 2298!1353 2298|1352 2299!1352 2299|1347 2298!1347 2298|1347 2299!1347 2299|1288 2299!1288 2299[1294 2296 1301 2292!1301 2292[1315 2285 1321
 2284!1321 2284[1320 2279 1315 2274!1315 2274[1302 2264 1258 2271!1258 2271[1248 2273 1209 2325!1209 2325|1209 2449!1209 2449|1313 2449!1313 2449[1360 2449 1375 2444!1375 2444[1385 2441 1386 2434!1386 2434[1389 2417 1383 2417!1383 2417
|1347 2407!1347 2407|1385 2402!1385 2402[1391 2402 1391 2390!1391 2390[1391 2378 1382 2376!1382 2376|1353 2369!1353 2369|1382 2362!1382 2362[1390 2361 1390 2350!1390 2350[1390 2341 1383 2340!1383 2340|1354 2334"/>
                    <Edge cubics="!1353 2298(;1353,2298 1352,2299 1352,2299q1353 2298 1352 2299);"/>
                    <Edge cubics="!1352 2299(;1350,2298 1349,2298 1347,2298q1352 2299 1347 2298);"/>
                    <Edge cubics="!1347 2298(;1347,2298 1347,2299 1347,2299q1347 2298 1347 2299);"/>
                    <Edge cubics="!1347 2299(;1347,2299 1288,2299 1288,2299q1347 2299 1288 2299);"/>
                    <Edge cubics="!1288 2299(;1288,2299 1311,2285 1321,2284q1288 2299Q1294 2296q1301 2292Q1315 2285q1321 2284);"/>
                    <Edge cubics="!1321 2284(;1320,2278 1318,2277 1315,2274q1321 2284Q1320 2279q1315 2274);"/>
                    <Edge cubics="!1315 2274(;1306,2267 1287,2266 1258,2271q1315 2274Q1302 2264q1258 2271);"/>
                    <Edge cubics="!1258 2271(;1252,2272 1227,2301 1209,2325q1258 2271Q1248 2273q1209 2325);"/>
                    <Edge cubics="!1209 2325(;1209,2325 1209,2449 1209,2449q1209 2325 1209 2449);"/>
                    <Edge cubics="!1209 2449(;1229,2449 1269,2449 1313,2449q1209 2449 1313 2449);"/>
                    <Edge cubics="!1313 2449(;1383,2449 1385,2441 1386,2434q1313 2449Q1360 2449q1375 2444Q1385 2441q1386 2434);"/>
                    <Edge cubics="!1386 2434(;1388,2423 1385,2417 1383,2417q1386 2434Q1389 2417q1383 2417);"/>
                    <Edge cubics="!1383 2417(;1383,2417 1347,2407 1347,2407q1383 2417 1347 2407);"/>
                    <Edge cubics="!1347 2407(;1347,2407 1385,2402 1385,2402q1347 2407 1385 2402);"/>
                    <Edge cubics="!1385 2402(;1388,2402 1391,2397 1391,2390q1385 2402Q1391 2402q1391 2390);"/>
                    <Edge cubics="!1391 2390(;1391,2388 1390,2378 1382,2376q1391 2390Q1391 2378q1382 2376);"/>
                    <Edge cubics="!1382 2376(;1382,2376 1353,2369 1353,2369q1382 2376 1353 2369);"/>
                    <Edge cubics="!1353 2369(;1353,2369 1382,2362 1382,2362q1353 2369 1382 2362);"/>
                    <Edge cubics="!1382 2362(;1388,2361 1390,2355 1390,2350q1382 2362Q1390 2361q1390 2350);"/>
                    <Edge cubics="!1390 2350(;1390,2347 1390,2341 1383,2340q1390 2350Q1390 2341q1383 2340);"/>
                    <Edge cubics="!1383 2340(;1383,2340 1354,2334 1354,2334q1383 2340 1354 2334);"/>
                    <Edge cubics="!1354 2334(;1354,2334 1465,2328 1465,2328q1354 2334 1465 2328);"/>
                    <Edge cubics="!1465 2328(;1475,2328 1483,2323 1483,2313q1465 2328Q1483 2328q1483 2313);"/>
                    <Edge cubics="!1483 2313(;1483,2303 1475,2298 1465,2298q1483 2313Q1483 2298q1465 2298);"/>
                    <Edge cubics="!1465 2298(;1465,2298 1353,2298 1353,2298q1465 2298 1353 2298);"/>
                  </edges>
                </DOMShape>
                <DOMShape selected="true" isDrawingObject="true">
                  <matrix>
                    <Matrix tx="-74.65" ty="-117.9"/>
                  </matrix>
                  <fills>
                    <FillStyle index="1">
                      <SolidColor color="#FE8F17"/>
                    </FillStyle>
                  </fills>
                  <edges>
                    <Edge fillStyle1="1" edges="
!1522 2298|1634 2298!1634 2298|1635 2299!1635 2299|1640 2298!1640 2298|1640 2299!1640 2299|1699 2299!1699 2299[1675 2285 1666 2284!1666 2284[1667 2279 1672 2274!1672 2274[1686 2263 1728 2271!1728 2271[1740 2273 1777 2325!1777 2325|1777
 2449!1777 2449|1674 2449!1674 2449[1627 2449 1611 2444!1611 2444[1602 2441 1601 2434!1601 2434[1598 2417 1603 2417!1603 2417|1639 2407!1639 2407|1602 2402!1602 2402[1596 2402 1596 2390!1596 2390[1596 2378 1604 2376!1604 2376|1634 2369
!1634 2369|1604 2362!1604 2362[1596 2360 1596 2350!1596 2350[1596 2341 1604 2340!1604 2340|1633 2334!1633 2334|1522 2328!1522 2328[1504 2328 1504 2313!1504 2313[1504 2298 1522 2298"/>
                    <Edge cubics="!1634 2298(;1634,2298 1635,2299 1635,2299q1634 2298 1635 2299);"/>
                    <Edge cubics="!1635 2299(;1636,2298 1638,2298 1640,2298q1635 2299 1640 2298);"/>
                    <Edge cubics="!1640 2298(;1640,2298 1640,2299 1640,2299q1640 2298 1640 2299);"/>
                    <Edge cubics="!1640 2299(;1640,2299 1699,2299 1699,2299q1640 2299 1699 2299);"/>
                    <Edge cubics="!1699 2299(;1699,2299 1675,2285 1666,2284q1699 2299Q1675 2285q1666 2284);"/>
                    <Edge cubics="!1666 2284(;1667,2278 1669,2277 1672,2274q1666 2284Q1667 2279q1672 2274);"/>
                    <Edge cubics="!1672 2274(;1681,2267 1700,2266 1728,2271q1672 2274Q1686 2263q1728 2271);"/>
                    <Edge cubics="!1728 2271(;1735,2272 1760,2301 1777,2325q1728 2271Q1740 2273q1777 2325);"/>
                    <Edge cubics="!1777 2325(;1777,2325 1777,2449 1777,2449q1777 2325 1777 2449);"/>
                    <Edge cubics="!1777 2449(;1757,2449 1718,2449 1674,2449q1777 2449 1674 2449);"/>
                    <Edge cubics="!1674 2449(;1603,2449 1602,2441 1601,2434q1674 2449Q1627 2449q1611 2444Q1602 2441q1601 2434);"/>
                    <Edge cubics="!1601 2434(;1599,2423 1602,2417 1603,2417q1601 2434Q1598 2417q1603 2417);"/>
                    <Edge cubics="!1603 2417(;1603,2417 1639,2407 1639,2407q1603 2417 1639 2407);"/>
                    <Edge cubics="!1639 2407(;1639,2407 1602,2402 1602,2402q1639 2407 1602 2402);"/>
                    <Edge cubics="!1602 2402(;1599,2402 1596,2397 1596,2390q1602 2402Q1596 2402q1596 2390);"/>
                    <Edge cubics="!1596 2390(;1596,2388 1596,2378 1604,2376q1596 2390Q1596 2378q1604 2376);"/>
                    <Edge cubics="!1604 2376(;1604,2376 1634,2369 1634,2369q1604 2376 1634 2369);"/>
                    <Edge cubics="!1634 2369(;1634,2369 1604,2362 1604,2362q1634 2369 1604 2362);"/>
                    <Edge cubics="!1604 2362(;1599,2361 1596,2355 1596,2350q1604 2362Q1596 2360q1596 2350);"/>
                    <Edge cubics="!1596 2350(;1596,2347 1597,2341 1604,2340q1596 2350Q1596 2341q1604 2340);"/>
                    <Edge cubics="!1604 2340(;1604,2340 1633,2334 1633,2334q1604 2340 1633 2334);"/>
                    <Edge cubics="!1633 2334(;1633,2334 1522,2328 1522,2328q1633 2334 1522 2328);"/>
                    <Edge cubics="!1522 2328(;1512,2328 1504,2323 1504,2313q1522 2328Q1504 2328q1504 2313);"/>
                    <Edge cubics="!1504 2313(;1504,2303 1512,2298 1522,2298q1504 2313Q1504 2298q1522 2298);"/>
                    <Edge cubics="!1522 2298(;1522,2298 1634,2298 1634,2298q1522 2298 1634 2298);"/>
                  </edges>
                </DOMShape>
              </elements>
            </DOMFrame>
          </frames>
        </DOMLayer>
      </layers>
    </DOMTimeline>
  </timeline>
</DOMSymbolItem>